git_copilot_commit/__init__.py
git_copilot_commit/cli.py
git_copilot_commit/git.py
git_copilot_commit/py.typed
git_copilot_commit/settings.py
git_copilot_commit/version.py
git_copilot_commit/prompts/commit-message-generator-prompt.md
git_copilot_commit-0.3.5.dist-info/METADATA
git_copilot_commit-0.3.5.dist-info/WHEEL
git_copilot_commit-0.3.5.dist-info/entry_points.txt
git_copilot_commit-0.3.5.dist-info/licenses/LICENSE
git_copilot_commit-0.3.5.dist-info/RECORD
