Metadata-Version: 2.4
Name: git-copilot-commit
Version: 0.3.5
Summary: Automatically generate and commit changes using copilot
Author-email: Dheepak Krishnamurthy <1813121+kdheepak@users.noreply.github.com>
License-File: LICENSE
Requires-Python: >=3.12
Requires-Dist: litellm>=1.75.4
Requires-Dist: platformdirs>=4.0.0
Requires-Dist: rich>=14.0.0
Requires-Dist: typer>=0.16.0
